{
  "id": "card_n_c402c51af593",
  "kind": "note",
  "title": "Augustine, Confessions §aug_conf_08_026: The very toys of toys, and vanities of vanities, my ancient mistresses, still...",
  "body": "The very toys of toys, and vanities of vanities, my ancient mistresses, still held me; they plucked my fleshy garment, and whispered softly, \"Dost thou cast us off? and from that moment shall we no more be with thee for ever? and from that moment shall not this or that be lawful for thee for ever?\" And what was it which they suggested in that I said, \"this or that,\" what did they suggest, O my God? Let Thy mercy turn it away from the soul of Thy servant. What defilements did they suggest! what shame! And now I much less than half heard them, and not openly showing themselves and contradicting me, but muttering as it were behind my back, and privily plucking me, as I was departing, but to look back on them. Yet they did retard me, so that I hesitated to burst and shake myself free from them, and to spring over whither I was called; a violent habit saying to me, \"Thinkest thou, thou canst live without them?\"",
  "source": {
    "label": "Augustine, Confessions (c. AD 400)",
    "url": "/canon.html?ref=augustine_aug_conf_08_026",
    "ref": "aug_conf_08_026",
    "authority_tier": "father"
  },
  "shelf": "classics",
  "box": "augustine_confessions",
  "bands": [
    "augustine",
    "confessions",
    "father"
  ],
  "connections": [
    {
      "to_card_id": "card_n_c42c7b0d6437",
      "relationship": "same_section",
      "origin": "nesting_2026_06_12"
    },
    {
      "to_card_id": "card_n_c3de19275694",
      "relationship": "same_section",
      "origin": "nesting_2026_06_12"
    }
  ],
  "author": "engine",
  "created_at": "2026-05-19T13:20:57.860863+00:00",
  "updated_at": "2026-05-19T19:57:55.686740+00:00",
  "visibility": "public",
  "lifecycle_stage": "public",
  "volatility": "permanent",
  "metrics": {
    "paperclips_count": 0,
    "helpful_count": 0,
    "not_helpful_count": 0,
    "cite_count": 4,
    "walks_through_count": 0,
    "flagged_count": 0
  },
  "source_hash": "ca208725381059bf4c6ae43ca9c66aa73952c37fa1ee19c086b2658d8e59d394",
  "witnesses": [
    {
      "class": "manuscript_tradition",
      "label": "Patrologia Latina (Migne) vol. 32 — Confessions Latin text",
      "url": "https://patristica.net/latina/",
      "ref": "PL-32"
    },
    {
      "class": "critical_edition",
      "label": "Corpus Christianorum Series Latina (CCSL) 27 — Verheijen",
      "url": "https://www.corpuschristianorum.org/",
      "ref": "CCSL-27"
    },
    {
      "class": "translation",
      "label": "Pusey translation (1838) — Library of Fathers",
      "url": "https://www.ccel.org/ccel/schaff/npnf101.html",
      "ref": "Pusey-1838"
    },
    {
      "class": "translation",
      "label": "Pine-Coffin translation (Penguin Classics, 1961)",
      "ref": "Pine-Coffin-1961"
    },
    {
      "class": "republication",
      "label": "Internet Archive — Confessions (multiple editions)",
      "url": "https://archive.org/search?query=augustine+confessions",
      "ref": "IA-Confessions"
    },
    {
      "class": "republication",
      "label": "Project Gutenberg — Confessions",
      "url": "https://www.gutenberg.org/ebooks/3296",
      "ref": "PG-3296"
    },
    {
      "class": "citation_tradition",
      "label": "Aquinas, Summa Theologica — cites Confessions extensively",
      "ref": "Aquinas-ST"
    }
  ],
  "witness_status": "passed",
  "witness_status_reason": "7 witnesses across 5 independence classes: ['citation_tradition', 'critical_edition', 'manuscript_tradition', 'republication', 'translation']"
}