{
  "id": "card_n_91881c7756ff",
  "kind": "note",
  "title": "Augustine, Confessions §aug_conf_07_020: There is no soundness in them, whom aught of Thy creation displeaseth: as nei...",
  "body": "There is no soundness in them, whom aught of Thy creation displeaseth: as neither in me, when much which Thou hast made, displeased me. And because my soul durst not be displeased at my God, it would fain not account that Thine, which displeased it. Hence it had gone into the opinion of two substances, and had no rest, but talked idly. And returning thence, it had made to itself a God, through infinite measures of all space; and thought it to be Thee, and placed it in its heart; and had again become the temple of its own idol, to Thee abominable. But after Thou hadst soothed my head, unknown to me, and closed mine eyes that they should not behold vanity, I ceased somewhat of my former self, and my frenzy was lulled to sleep; and I awoke in Thee, and saw Thee infinite, but in another way, and this sight was not derived from the flesh.",
  "source": {
    "label": "Augustine, Confessions (c. AD 400)",
    "url": "/canon.html?ref=augustine_aug_conf_07_020",
    "ref": "aug_conf_07_020",
    "authority_tier": "father"
  },
  "shelf": "classics",
  "box": "augustine_confessions",
  "bands": [
    "augustine",
    "confessions",
    "father"
  ],
  "connections": [
    {
      "to_card_id": "card_n_91aee00da40a",
      "relationship": "same_section",
      "origin": "nesting_2026_06_12"
    },
    {
      "to_card_id": "card_n_914fdb635253",
      "relationship": "same_section",
      "origin": "nesting_2026_06_12"
    }
  ],
  "author": "engine",
  "created_at": "2026-05-19T13:20:57.815553+00:00",
  "updated_at": "2026-05-19T19:57:55.441665+00:00",
  "visibility": "public",
  "lifecycle_stage": "public",
  "volatility": "permanent",
  "metrics": {
    "paperclips_count": 0,
    "helpful_count": 0,
    "not_helpful_count": 0,
    "cite_count": 4,
    "walks_through_count": 0,
    "flagged_count": 0
  },
  "source_hash": "bac76e583a61163164ef7fd6b3b922ea4cfe27941a4063c438636d5d30871598",
  "witnesses": [
    {
      "class": "manuscript_tradition",
      "label": "Patrologia Latina (Migne) vol. 32 — Confessions Latin text",
      "url": "https://patristica.net/latina/",
      "ref": "PL-32"
    },
    {
      "class": "critical_edition",
      "label": "Corpus Christianorum Series Latina (CCSL) 27 — Verheijen",
      "url": "https://www.corpuschristianorum.org/",
      "ref": "CCSL-27"
    },
    {
      "class": "translation",
      "label": "Pusey translation (1838) — Library of Fathers",
      "url": "https://www.ccel.org/ccel/schaff/npnf101.html",
      "ref": "Pusey-1838"
    },
    {
      "class": "translation",
      "label": "Pine-Coffin translation (Penguin Classics, 1961)",
      "ref": "Pine-Coffin-1961"
    },
    {
      "class": "republication",
      "label": "Internet Archive — Confessions (multiple editions)",
      "url": "https://archive.org/search?query=augustine+confessions",
      "ref": "IA-Confessions"
    },
    {
      "class": "republication",
      "label": "Project Gutenberg — Confessions",
      "url": "https://www.gutenberg.org/ebooks/3296",
      "ref": "PG-3296"
    },
    {
      "class": "citation_tradition",
      "label": "Aquinas, Summa Theologica — cites Confessions extensively",
      "ref": "Aquinas-ST"
    }
  ],
  "witness_status": "passed",
  "witness_status_reason": "7 witnesses across 5 independence classes: ['citation_tradition', 'critical_edition', 'manuscript_tradition', 'republication', 'translation']"
}