{
  "id": "card_n_15bc196ee012",
  "kind": "note",
  "title": "Aurelius, Meditations §aur_05_xii: What those things are in themselves, which by the greatest part are esteemed ...",
  "body": "What those things are in themselves, which by the greatest part are esteemed good, thou mayest gather even from this. For if a man shall hear things mentioned as good, which are really good indeed, such as are prudence, temperance, justice, fortitude, after so much heard and conceived, he cannot endure to hear of any more, for the word good is properly spoken of them. But as for those which by the vulgar are esteemed good, if he shall hear them mentioned as good, he doth hearken for more. He is well contented to hear, that what is spoken by the comedian, is but familiarly and popularly spoken, so that even the vulgar apprehend the difference. For why is it else, that this offends not and needs not to be excused, when virtues are styled good: but that which is spoken in commendation of wealth, pleasure, or honour, we entertain it only as merrily and pleasantly spoken? Proceed therefore, and inquire further, whether it may not be that those things also which being mentioned upon the stage were merrily, and with great applause of the multitude, scoffed at with this jest, that they that possessed them had not in all the world of their own, (such was their affluence and plenty) so much as a place where to avoid their excrements. Whether, I say, those ought not also in very deed to be much respected, and esteemed of, as the only things that are truly good.",
  "source": {
    "label": "Marcus Aurelius, Meditations (c. AD 170)",
    "url": "/canon.html?ref=aurelius_aur_05_xii",
    "ref": "aur_05_xii",
    "authority_tier": "external_aligned"
  },
  "shelf": "classics",
  "box": "aurelius_meditations",
  "bands": [
    "aurelius",
    "meditations",
    "stoic",
    "pre_christian"
  ],
  "connections": [
    {
      "to_card_id": "card_n_1607e57e890c",
      "relationship": "same_section",
      "origin": "nesting_2026_06_12"
    },
    {
      "to_card_id": "card_n_139e4c631dc0",
      "relationship": "same_section",
      "origin": "nesting_2026_06_12"
    }
  ],
  "author": "engine",
  "created_at": "2026-05-19T13:20:58.227615+00:00",
  "updated_at": "2026-05-19T19:57:55.774509+00:00",
  "visibility": "public",
  "lifecycle_stage": "public",
  "volatility": "permanent",
  "metrics": {
    "paperclips_count": 0,
    "helpful_count": 0,
    "not_helpful_count": 0,
    "cite_count": 4,
    "walks_through_count": 0,
    "flagged_count": 0
  },
  "source_hash": "484b54b4c4e620a9c00d0f065b093b439b3ebd8af5490d1aabf1d7b316626042",
  "witnesses": [
    {
      "class": "manuscript_tradition",
      "label": "Vaticanus Graecus 1950 — earliest complete Greek MS",
      "ref": "Vat-Gr-1950"
    },
    {
      "class": "critical_edition",
      "label": "Dalfen, Marci Aurelii Antonini Ad Se Ipsum Libri XII (Teubner 1987)",
      "ref": "Dalfen-Teubner"
    },
    {
      "class": "translation",
      "label": "George Long translation (1862) — public domain English",
      "url": "https://www.gutenberg.org/ebooks/2680",
      "ref": "Long-1862"
    },
    {
      "class": "translation",
      "label": "Hays translation (Modern Library, 2002)",
      "ref": "Hays-2002"
    },
    {
      "class": "republication",
      "label": "Internet Archive — Meditations Long translation",
      "url": "https://archive.org/details/meditations00auregoog",
      "ref": "IA-Meditations"
    }
  ],
  "witness_status": "passed",
  "witness_status_reason": "5 witnesses across 4 independence classes: ['critical_edition', 'manuscript_tradition', 'republication', 'translation']"
}