{
  "id": "card_n_700c3952ec78",
  "kind": "note",
  "title": "Easton: Pekah",
  "body": "Open-eyed, the son of Remaliah a captain in the army of Pekahiah, king of Israel, whom he slew, with the aid of a band of Gileadites, and succeeded (B.C. 758) on the throne (2 Kings 15:25). Seventeen years after this he entered into an alliance with Rezin, king of Syria, and took part with him in besieging Jerusalem (2 Kings 15:37; 16:5). But Tiglath-pilser, who was in alliance with Ahaz, king of Judah, came up against Pekah, and carried away captive many of the inhabitants of his kingdom (2 Kings 15:29). This was the beginning of the “Captivity.” Soon after this Pekah was put to death by Hoshea, the son of Elah, who usurped the throne (2 Kings 15:30; 16:1-9. Comp. Isa. 7:16; 8:4; 9:12). He is supposed by some to have been the “shephard” mentioned in Zech. 11:16.",
  "source": {
    "label": "Matthew Easton, Illustrated Bible Dictionary (1897)",
    "url": "/encyclopedia.html?ref=Pekah",
    "ref": "Pekah",
    "authority_tier": "external_aligned"
  },
  "shelf": "dictionary",
  "box": "easton_person_m_p",
  "bands": [
    "easton",
    "bible_dictionary",
    "person"
  ],
  "connections": [
    {
      "to_card_id": "card_n_714975e2e0d5",
      "relationship": "same_section",
      "origin": "nesting_2026_06_12"
    },
    {
      "to_card_id": "card_n_6b7d3781cf66",
      "relationship": "same_section",
      "origin": "nesting_2026_06_12"
    }
  ],
  "author": "engine",
  "created_at": "2026-05-19T13:11:11.493305+00:00",
  "updated_at": "2026-05-19T19:50:39.718953+00:00",
  "visibility": "public",
  "lifecycle_stage": "public",
  "volatility": "permanent",
  "metrics": {
    "paperclips_count": 0,
    "helpful_count": 0,
    "not_helpful_count": 0,
    "cite_count": 0,
    "walks_through_count": 0,
    "flagged_count": 0
  },
  "source_hash": "0d92e59b70e54e3f9cb8fd4094870ddd938a005c6fbc2348f4d00787a25f64fc",
  "witnesses": [
    {
      "class": "manuscript_tradition",
      "label": "Original 1897 publication — Thomas Nelson, London",
      "ref": "Easton-1897"
    },
    {
      "class": "republication",
      "label": "Project Gutenberg — Easton's Bible Dictionary",
      "url": "https://www.gutenberg.org/ebooks/45696",
      "ref": "PG-45696"
    },
    {
      "class": "republication",
      "label": "Internet Archive — multiple scans",
      "url": "https://archive.org/details/eastonsillustra00east",
      "ref": "IA-Easton"
    },
    {
      "class": "republication",
      "label": "CCEL — Easton's Bible Dictionary",
      "url": "https://www.ccel.org/e/easton/ebd/",
      "ref": "CCEL-Easton"
    },
    {
      "class": "republication",
      "label": "Blue Letter Bible — searchable Easton's",
      "url": "https://www.blueletterbible.org/study/easton/",
      "ref": "BLB-Easton"
    }
  ],
  "witness_status": "passed",
  "witness_status_reason": "5 witnesses across 2 independence classes: ['manuscript_tradition', 'republication']"
}