{
  "id": "card_c_182121b8100a",
  "kind": "connection",
  "title": "Easton: Lawyer cites Luke",
  "body": "Card references Luke. Auto-detected via book-name match.",
  "source": {
    "label": "Auto-detected citation",
    "url": "",
    "ref": "",
    "authority_tier": "engine_derived"
  },
  "shelf": "connections",
  "box": "dictionary_cites_luke",
  "bands": [
    "cites",
    "auto_detected",
    "dictionary",
    "luke"
  ],
  "connections": [
    {
      "to_card_id": "card_n_e3cc1fddda9d",
      "relationship": "see_also"
    },
    {
      "to_card_id": "card_n_ee545b228696",
      "relationship": "see_also"
    }
  ],
  "author": "engine",
  "created_at": "2026-05-19T13:34:20.509605+00:00",
  "updated_at": "2026-05-19T19:49:22.971873+00:00",
  "visibility": "public",
  "lifecycle_stage": "public",
  "volatility": "stable",
  "metrics": {
    "paperclips_count": 0,
    "helpful_count": 0,
    "not_helpful_count": 0,
    "cite_count": 0,
    "walks_through_count": 0,
    "flagged_count": 0
  },
  "extra": {
    "left_card_id": "card_n_e3cc1fddda9d",
    "right_card_id": "card_n_ee545b228696",
    "relationship_kind": "cites",
    "explanation": "Auto-detected: Luke named in dictionary body.",
    "bidirectional": true
  },
  "source_hash": "14378438354f249733ccb70ea6b4779c04fcedb7c16a1f54fa5ee21aee607669",
  "witnesses": [
    {
      "class": "inherited",
      "label": "inherited from 2 parent cards",
      "ref": "card_n_e3cc1fddda9d,card_n_ee545b228696"
    }
  ],
  "witness_status": "passed",
  "witness_status_reason": "inherits from 2 passed parents across 5 classes"
}