{
  "id": "card_c_4fa9a310f589",
  "kind": "connection",
  "title": "Easton: Lamentations, Book of cites Jeremiah",
  "body": "Card references Jeremiah. Auto-detected via book-name match.",
  "source": {
    "label": "Auto-detected citation",
    "url": "",
    "ref": "",
    "authority_tier": "engine_derived"
  },
  "shelf": "connections",
  "box": "dictionary_cites_jeremiah",
  "bands": [
    "cites",
    "auto_detected",
    "dictionary",
    "jeremiah"
  ],
  "connections": [
    {
      "to_card_id": "card_n_2e6ce5fca91a",
      "relationship": "see_also"
    },
    {
      "to_card_id": "card_n_bd88880279be",
      "relationship": "see_also"
    }
  ],
  "author": "engine",
  "created_at": "2026-05-19T13:33:59.040397+00:00",
  "updated_at": "2026-05-19T19:49:24.455566+00:00",
  "visibility": "public",
  "lifecycle_stage": "public",
  "volatility": "stable",
  "metrics": {
    "paperclips_count": 0,
    "helpful_count": 0,
    "not_helpful_count": 0,
    "cite_count": 0,
    "walks_through_count": 0,
    "flagged_count": 0
  },
  "extra": {
    "left_card_id": "card_n_2e6ce5fca91a",
    "right_card_id": "card_n_bd88880279be",
    "relationship_kind": "cites",
    "explanation": "Auto-detected: Jeremiah named in dictionary body.",
    "bidirectional": true
  },
  "source_hash": "cf3514057bd04e54260c8035603c4aab6a1aa87be40f60bcaa10cb61d784d63a",
  "witnesses": [
    {
      "class": "inherited",
      "label": "inherited from 2 parent cards",
      "ref": "card_n_2e6ce5fca91a,card_n_bd88880279be"
    }
  ],
  "witness_status": "passed",
  "witness_status_reason": "inherits from 2 passed parents across 5 classes"
}