{
  "id": "card_c_470cd87c1f24",
  "kind": "connection",
  "title": "Polycarp to the Philippians I cites Philippians",
  "body": "Patristic text references Philippians. Detected via name match in the chapter body.",
  "source": {
    "label": "Auto-detected citation",
    "url": "",
    "ref": "",
    "authority_tier": "engine_derived"
  },
  "shelf": "connections",
  "box": "patristics_cites_philippians",
  "bands": [
    "cites",
    "patristics",
    "philippians",
    "auto_detected"
  ],
  "connections": [
    {
      "to_card_id": "card_n_3a794cd9373c",
      "relationship": "see_also"
    },
    {
      "to_card_id": "card_n_5c3f598f3de3",
      "relationship": "see_also"
    }
  ],
  "author": "engine",
  "created_at": "2026-05-19T12:49:13.637560+00:00",
  "updated_at": "2026-05-19T19:50:02.398529+00:00",
  "visibility": "public",
  "lifecycle_stage": "public",
  "volatility": "stable",
  "metrics": {
    "paperclips_count": 0,
    "helpful_count": 0,
    "not_helpful_count": 0,
    "cite_count": 0,
    "walks_through_count": 0,
    "flagged_count": 0
  },
  "extra": {
    "left_card_id": "card_n_3a794cd9373c",
    "right_card_id": "card_n_5c3f598f3de3",
    "relationship_kind": "cites",
    "explanation": "Auto-detected: Philippians named in patristic body.",
    "bidirectional": true
  },
  "source_hash": "239a0435aaf9dd4913063093ae304779e5daf196c664f504e196dde61b4da2ae",
  "witnesses": [
    {
      "class": "inherited",
      "label": "inherited from 2 parent cards",
      "ref": "card_n_3a794cd9373c,card_n_5c3f598f3de3"
    }
  ],
  "witness_status": "passed",
  "witness_status_reason": "inherits from 2 passed parents across 5 classes"
}