{
  "id": "card_n_8b7bcab57e12",
  "kind": "note",
  "title": "Easton: Fold",
  "body": "An enclosure for flocks to rest together (Isa. 13:20). Sheep-folds are mentioned Num. 32:16, 24, 36; 2 Sam. 7:8; Zeph. 2:6; John 10:1, etc. It was prophesied of the cities of Ammon (Ezek. 25:5), Aroer (Isa. 17:2), and Judaea, that they would be folds or couching-places for flocks. “Among the pots,” of the Authorized Version (Ps. 68:13), is rightly in the Revised Version, “among the sheepfolds.”",
  "source": {
    "label": "Matthew Easton, Illustrated Bible Dictionary (1897)",
    "url": "/encyclopedia.html?ref=Fold",
    "ref": "Fold",
    "authority_tier": "external_aligned"
  },
  "shelf": "dictionary",
  "box": "easton_concept_e_h",
  "bands": [
    "easton",
    "bible_dictionary",
    "concept"
  ],
  "connections": [
    {
      "to_card_id": "card_n_59aff31da66d",
      "relationship": "cites",
      "via_connection_card_id": "card_c_055da11d8282"
    }
  ],
  "author": "engine",
  "created_at": "2026-05-19T13:11:10.312158+00:00",
  "updated_at": "2026-05-19T19:50:28.120408+00:00",
  "visibility": "public",
  "lifecycle_stage": "public",
  "volatility": "permanent",
  "metrics": {
    "paperclips_count": 0,
    "helpful_count": 0,
    "not_helpful_count": 0,
    "cite_count": 2,
    "walks_through_count": 0,
    "flagged_count": 0
  },
  "source_hash": "24d39a080cf8f23090e4f920af8f8f9986303948871debf726a5f23959c069d4",
  "witnesses": [
    {
      "class": "manuscript_tradition",
      "label": "Original 1897 publication — Thomas Nelson, London",
      "ref": "Easton-1897"
    },
    {
      "class": "republication",
      "label": "Project Gutenberg — Easton's Bible Dictionary",
      "url": "https://www.gutenberg.org/ebooks/45696",
      "ref": "PG-45696"
    },
    {
      "class": "republication",
      "label": "Internet Archive — multiple scans",
      "url": "https://archive.org/details/eastonsillustra00east",
      "ref": "IA-Easton"
    },
    {
      "class": "republication",
      "label": "CCEL — Easton's Bible Dictionary",
      "url": "https://www.ccel.org/e/easton/ebd/",
      "ref": "CCEL-Easton"
    },
    {
      "class": "republication",
      "label": "Blue Letter Bible — searchable Easton's",
      "url": "https://www.blueletterbible.org/study/easton/",
      "ref": "BLB-Easton"
    }
  ],
  "witness_status": "passed",
  "witness_status_reason": "5 witnesses across 2 independence classes: ['manuscript_tradition', 'republication']"
}