{
  "id": "card_n_5089354dc7ee",
  "kind": "note",
  "title": "Pilgrim's Progress §132: So in the morning they all got up; and, after some more discourse, they told him that h...",
  "body": "So in the morning they all got up; and, after some more discourse, they told him that he should not depart till they had shown him the rarities of that place. And first they had him into the study, where they showed him records of the greatest antiquity; in which, as I remember my dream, they showed him first the pedigree of the Lord of the hill, that he was the son of the Ancient of Days, and came by that eternal generation. Here also was more fully recorded the acts that he had done, and the names of many hundreds that he had taken into his service; and how he had placed them in such habitations that could neither by length of days, nor decays of nature, be dissolved.",
  "source": {
    "label": "John Bunyan, Pilgrim's Progress (1678)",
    "url": "/canon.html?ref=pilgrim_132",
    "ref": "§132",
    "authority_tier": "external_aligned"
  },
  "shelf": "classics",
  "box": "pilgrims_progress",
  "bands": [
    "pilgrim",
    "bunyan",
    "allegory"
  ],
  "connections": [
    {
      "to_card_id": "card_n_518a78a3fc86",
      "relationship": "same_section",
      "origin": "nesting_2026_06_12"
    },
    {
      "to_card_id": "card_n_5047b0fe5f14",
      "relationship": "same_section",
      "origin": "nesting_2026_06_12"
    }
  ],
  "author": "engine",
  "created_at": "2026-05-19T13:07:21.346996+00:00",
  "updated_at": "2026-05-19T19:57:55.256766+00:00",
  "visibility": "public",
  "lifecycle_stage": "public",
  "volatility": "permanent",
  "metrics": {
    "paperclips_count": 0,
    "helpful_count": 0,
    "not_helpful_count": 0,
    "cite_count": 4,
    "walks_through_count": 0,
    "flagged_count": 0
  },
  "source_hash": "b36520f9826c129e4622bd70cff367774754dad6672798df331daea0e04b05a9",
  "witnesses": [
    {
      "class": "manuscript_tradition",
      "label": "First edition Nathaniel Ponder, London 1678 — original imprint",
      "ref": "Ponder-1678"
    },
    {
      "class": "critical_edition",
      "label": "Oxford World's Classics — Roger Sharrock, 1960/1984",
      "ref": "Sharrock-OWC"
    },
    {
      "class": "republication",
      "label": "Project Gutenberg — Pilgrim's Progress",
      "url": "https://www.gutenberg.org/ebooks/131",
      "ref": "PG-131"
    },
    {
      "class": "republication",
      "label": "Internet Archive — multiple editions",
      "url": "https://archive.org/search?query=pilgrim%27s+progress+bunyan",
      "ref": "IA-Bunyan"
    },
    {
      "class": "non_government_archive",
      "label": "Christian Classics Ethereal Library",
      "url": "https://www.ccel.org/ccel/bunyan/pilgrim.html",
      "ref": "CCEL-Bunyan"
    },
    {
      "class": "citation_tradition",
      "label": "Cited extensively by Spurgeon, Edwards, modern Reformed writers",
      "ref": "Spurgeon-Edwards-cites"
    }
  ],
  "witness_status": "passed",
  "witness_status_reason": "6 witnesses across 5 independence classes: ['citation_tradition', 'critical_edition', 'manuscript_tradition', 'non_government_archive', 'republication']"
}