{
  "id": "card_n_536d071b9bb5",
  "kind": "note",
  "title": "Easton: Flour",
  "body": "Grain reduced to the form of meal is spoken of in the time of Abraham (Gen. 18:6). As baking was a daily necessity, grain was also ground daily at the mills (Jer. 25:10). The flour mingled with water was kneaded in kneading-troughs, and sometimes leaven (Ex. 12:34) was added and sometimes omitted (Gen. 19:3). The dough was then formed into thin cakes nine or ten inches in diameter and baked in the oven. Fine flour was offered by the poor as a sin-offering (Lev. 5:11-13), and also in connection with other sacrifices (Num. 15:3-12; 28:7-29).",
  "source": {
    "label": "Matthew Easton, Illustrated Bible Dictionary (1897)",
    "url": "/encyclopedia.html?ref=Flour",
    "ref": "Flour",
    "authority_tier": "external_aligned"
  },
  "shelf": "dictionary",
  "box": "easton_concept_e_h",
  "bands": [
    "easton",
    "bible_dictionary",
    "concept"
  ],
  "connections": [
    {
      "to_card_id": "card_n_56e151b61acf",
      "relationship": "same_section",
      "origin": "nesting_2026_06_12"
    },
    {
      "to_card_id": "card_n_52bf2278f05b",
      "relationship": "same_section",
      "origin": "nesting_2026_06_12"
    }
  ],
  "author": "engine",
  "created_at": "2026-05-19T13:08:59.519576+00:00",
  "updated_at": "2026-05-19T19:50:27.406159+00:00",
  "visibility": "public",
  "lifecycle_stage": "public",
  "volatility": "permanent",
  "metrics": {
    "paperclips_count": 0,
    "helpful_count": 0,
    "not_helpful_count": 0,
    "cite_count": 0,
    "walks_through_count": 0,
    "flagged_count": 0
  },
  "source_hash": "f28c373a63257856e76fc04bb499e276c0846d9221267e2f7ae879b98e9dd65f",
  "witnesses": [
    {
      "class": "manuscript_tradition",
      "label": "Original 1897 publication — Thomas Nelson, London",
      "ref": "Easton-1897"
    },
    {
      "class": "republication",
      "label": "Project Gutenberg — Easton's Bible Dictionary",
      "url": "https://www.gutenberg.org/ebooks/45696",
      "ref": "PG-45696"
    },
    {
      "class": "republication",
      "label": "Internet Archive — multiple scans",
      "url": "https://archive.org/details/eastonsillustra00east",
      "ref": "IA-Easton"
    },
    {
      "class": "republication",
      "label": "CCEL — Easton's Bible Dictionary",
      "url": "https://www.ccel.org/e/easton/ebd/",
      "ref": "CCEL-Easton"
    },
    {
      "class": "republication",
      "label": "Blue Letter Bible — searchable Easton's",
      "url": "https://www.blueletterbible.org/study/easton/",
      "ref": "BLB-Easton"
    }
  ],
  "witness_status": "passed",
  "witness_status_reason": "5 witnesses across 2 independence classes: ['manuscript_tradition', 'republication']"
}